aggin/__init__.py
aggin/aggin.py
aggin/shell.py
aggin/strings_with_arrows.py
aggin-0.3.7.dist-info/METADATA
aggin-0.3.7.dist-info/WHEEL
aggin-0.3.7.dist-info/entry_points.txt
aggin-0.3.7.dist-info/top_level.txt
aggin-0.3.7.dist-info/RECORD
