Metadata-Version: 2.1
Name: aggin
Version: 0.3.7
Summary: My Custom Programming Language
Author: Aman
